pyfenstein3d/__init__.py
pyfenstein3d/__main__.py
pyfenstein3d/engine/__init__.py
pyfenstein3d/engine/animation.py
pyfenstein3d/engine/block.py
pyfenstein3d/engine/config.py
pyfenstein3d/engine/decoration.py
pyfenstein3d/engine/door.py
pyfenstein3d/engine/enemy.py
pyfenstein3d/engine/field_of_view.py
pyfenstein3d/engine/item.py
pyfenstein3d/engine/item_ammo.py
pyfenstein3d/engine/item_grid.py
pyfenstein3d/engine/item_score.py
pyfenstein3d/engine/item_weapon.py
pyfenstein3d/engine/map2d.py
pyfenstein3d/engine/person.py
pyfenstein3d/engine/player.py
pyfenstein3d/engine/ray.py
pyfenstein3d/engine/server.py
pyfenstein3d/engine/vector2d.py
pyfenstein3d/engine/wall.py
pyfenstein3d/engine/weapon.py
pyfenstein3d/game/__init__.py
pyfenstein3d/game/command.py
pyfenstein3d/game/console_manager.py
pyfenstein3d/game/game.py
pyfenstein3d/game/image.py
pyfenstein3d/game/screen.py
pyfenstein3d/imgs/enemy-dog.png
pyfenstein3d/imgs/enemy-guard.png
pyfenstein3d/imgs/hud.png
pyfenstein3d/imgs/items.png
pyfenstein3d/imgs/walls.png
pyfenstein3d/imgs/weapons.png
pyfenstein3d/maps_pattern/map_1_level_1.txt
pyfenstein3d/maps_pattern/map_test.txt
pyfenstein3d-1.5.1.dist-info/LICENSE
pyfenstein3d-1.5.1.dist-info/METADATA
pyfenstein3d-1.5.1.dist-info/WHEEL
pyfenstein3d-1.5.1.dist-info/top_level.txt
pyfenstein3d-1.5.1.dist-info/RECORD
