Metadata-Version: 2.1
Name: pyfenstein3d
Version: 1.5.1
Summary: Projeto realizado em python com intuido educacional de tentar reproduzir o jogo Wolfenstein 3d no prompt de comando.
Home-page: https://github.com/GrrriiiM/pyfenstein3d
Author: Allison GrrriiiM
Author-email: allison.f.oliveira@hotmail.com
License: MIT License
Platform: UNKNOWN
Requires-Dist: numpy (==1.19.5)
Requires-Dist: keyboard (==0.13.5)
Requires-Dist: Pillow (==8.0.1)
Requires-Dist: pywin32 (==300)
